treetoolml/__init__.py
treetoolml/IndividualTreeExtraction/PointwiseDirectionPrediction_torch.py
treetoolml/IndividualTreeExtraction/__init__.py
treetoolml/IndividualTreeExtraction/accessible_region/AccessibleRegionGrowing.py
treetoolml/IndividualTreeExtraction/accessible_region/__init__.py
treetoolml/IndividualTreeExtraction/backbone_network/BatchSampleGenerator.py
treetoolml/IndividualTreeExtraction/backbone_network/BatchSampleGenerator_torch.py
treetoolml/IndividualTreeExtraction/backbone_network/Loss.py
treetoolml/IndividualTreeExtraction/backbone_network/Loss_torch.py
treetoolml/IndividualTreeExtraction/backbone_network/PDE_net_torch.py
treetoolml/IndividualTreeExtraction/backbone_network/__init__.py
treetoolml/IndividualTreeExtraction/center_detection/__init__.py
treetoolml/IndividualTreeExtraction/center_detection/center_detection.py
treetoolml/IndividualTreeExtraction/center_detection/center_detection_vis.py
treetoolml/IndividualTreeExtraction/utils/__init__.py
treetoolml/IndividualTreeExtraction/utils/py_util.py
treetoolml/IndividualTreeExtraction/voxel_traversal/VoxelTraversalAlgorithm.py
treetoolml/IndividualTreeExtraction/voxel_traversal/__init__.py
treetoolml/config/__init__.py
treetoolml/config/config.py
treetoolml/config/defaults.py
treetoolml/data/BatchSampleGenerator_torch.py
treetoolml/data/__init__.py
treetoolml/layers/Loss_torch.py
treetoolml/layers/__init__.py
treetoolml/model/RRFSegNet.py
treetoolml/model/__init__.py
treetoolml/model/build_arch.py
treetoolml/model/build_model.py
treetoolml/utils/PointwiseDirectionPrediction_torch.py
treetoolml/utils/REGISTRY.py
treetoolml/utils/__init__.py
treetoolml/utils/benchmark_util.py
treetoolml/utils/default_parser.py
treetoolml/utils/evaluation_metrics.py
treetoolml/utils/file_tracability.py
treetoolml/utils/py_util.py
treetoolml/utils/tictoc.py
treetoolml-1.0.1.dist-info/METADATA
treetoolml-1.0.1.dist-info/WHEEL
treetoolml-1.0.1.dist-info/top_level.txt
treetoolml-1.0.1.dist-info/RECORD
