Metadata-Version: 2.1
Name: treetoolml
Version: 1.0.1
Summary: Python package for tree detection, segmentation and extraction of DBH
Home-page: https://github.com/porteratzo/TreeToolML
Author: Omar Montoya
Author-email: omar.alfonso.montoya@hotmail.com
License: MIT License
Requires-Dist: treetool
Requires-Dist: open3d
Requires-Dist: numpy
Requires-Dist: pandas
Requires-Dist: matplotlib
Requires-Dist: lsq-ellipse
Requires-Dist: tqdm
Requires-Dist: yacs
Requires-Dist: plyfile
Requires-Dist: fvcore
Requires-Dist: tensorboard
Requires-Dist: torchsummary
